{
    "_prodSequences": {
        "name": "_prodSequences",
        "relationship": "hasMany",
        "renderer_view_all": "count",
        "renderer_view_all_param": "",
        "renderer_edit": "many_lines",
        "renderer_edit_param": "getManyLineParams",
        "control_name": "prodSequences"
    },
    "_subProject": {
        "name": "_subProject",
        "relationship": "belongsTo",
        "renderer_view_all": "column",
        "renderer_view_all_param": "name",
        "renderer_edit": "",
        "renderer_edit_param": "",
        "control_name": ""
    },
    "_prodRouting": {
        "name": "_prodRouting",
        "relationship": "belongsTo",
        "renderer_view_all": "column",
        "renderer_view_all_param": "name",
        "renderer_edit": "",
        "renderer_edit_param": "",
        "control_name": ""
    },
    "_qaqcInspChklsts": {
        "name": "_qaqcInspChklsts",
        "relationship": "hasMany",
        "renderer_view_all": "count",
        "renderer_view_all_param": "",
        "renderer_edit": "many_lines",
        "renderer_edit_param": "getManyLineParams",
        "control_name": "qaqcInspChklsts"
    }
}