{
    "_getChklst": {
        "name": "_getChklst",
        "relationship": "belongsTo",
        "control_name": "",
        "renderer_view_all": "column",
        "renderer_view_all_param": "name",
        "renderer_edit": "",
        "renderer_edit_param": "",
        "filter_columns": "",
        "filter_values": "",
        "radio_checkbox_colspan": ""
    },
    "_getSheet": {
        "name": "_getSheet",
        "relationship": "belongsTo",
        "control_name": "",
        "renderer_view_all": "column",
        "renderer_view_all_param": "description",
        "renderer_edit": "",
        "renderer_edit_param": "",
        "filter_columns": "",
        "filter_values": "",
        "radio_checkbox_colspan": ""
    },
    "_getGroup": {
        "name": "_getGroup",
        "relationship": "belongsTo",
        "control_name": "",
        "renderer_view_all": "column",
        "renderer_view_all_param": "description",
        "renderer_edit": "",
        "renderer_edit_param": "",
        "filter_columns": "",
        "filter_values": "",
        "radio_checkbox_colspan": ""
    },
    "_getControlGroup": {
        "name": "_getControlGroup",
        "relationship": "belongsTo",
        "control_name": "",
        "renderer_view_all": "",
        "renderer_view_all_param": "",
        "renderer_edit": "",
        "renderer_edit_param": "",
        "filter_columns": "",
        "filter_values": "",
        "radio_checkbox_colspan": ""
    },
    "_getControlValue": {
        "name": "_getControlValue",
        "relationship": "belongsTo",
        "control_name": "",
        "renderer_view_all": "column",
        "renderer_view_all_param": "name",
        "renderer_edit": "",
        "renderer_edit_param": "",
        "filter_columns": "",
        "filter_values": "",
        "radio_checkbox_colspan": ""
    },
    "_getFailDetail": {
        "name": "_getFailDetail",
        "relationship": "belongsToMany",
        "control_name": "",
        "renderer_view_all": "",
        "renderer_view_all_param": "",
        "renderer_edit": "",
        "renderer_edit_param": "",
        "filter_columns": "",
        "filter_values": "",
        "radio_checkbox_colspan": ""
    },
    "_getOnHoldDetail": {
        "name": "_getOnHoldDetail",
        "relationship": "belongsToMany",
        "control_name": "",
        "renderer_view_all": "",
        "renderer_view_all_param": "",
        "renderer_edit": "",
        "renderer_edit_param": "",
        "filter_columns": "",
        "filter_values": "",
        "radio_checkbox_colspan": ""
    },
    "_getOnHold()": {
        "name": "_getOnHold()",
        "relationship": "getCheckedByField",
        "control_name": "On Hold",
        "renderer_view_all": "column",
        "renderer_view_all_param": "name",
        "renderer_edit": "",
        "renderer_edit_param": "",
        "filter_columns": "qaqc_insp_control_value_id",
        "filter_values": "4",
        "radio_checkbox_colspan": ""
    },
    "_getFailed()": {
        "name": "_getFailed()",
        "relationship": "getCheckedByField",
        "control_name": "Failed",
        "renderer_view_all": "column",
        "renderer_view_all_param": "name",
        "renderer_edit": "",
        "renderer_edit_param": "",
        "filter_columns": "qaqc_insp_control_value_id",
        "filter_values": "2",
        "radio_checkbox_colspan": ""
    }
}