{
    "_id": {
        "name": "_id",
        "column_name": "id",
        "new": "true",
        "passed": "true",
        "failed": "true"
    },
    "_name": {
        "name": "_name",
        "column_name": "name",
        "new": "true",
        "passed": "true",
        "failed": "true"
    },
    "_description": {
        "name": "_description",
        "column_name": "description",
        "new": "true",
        "passed": "true",
        "failed": "true"
    },
    "_training_hours": {
        "name": "_training_hours",
        "column_name": "training_hours",
        "new": "true",
        "passed": "true",
        "failed": "true"
    },
    "_user_id": {
        "name": "_user_id",
        "column_name": "user_id",
        "new": "true",
        "passed": "true",
        "failed": "true"
    },
    "_hse_induction_id": {
        "name": "_hse_induction_id",
        "column_name": "hse_induction_id",
        "new": "true",
        "passed": "true",
        "failed": "true"
    },
    "_owner_id": {
        "name": "_owner_id",
        "column_name": "owner_id",
        "new": "true",
        "passed": "true",
        "failed": "true"
    },
    "_status": {
        "name": "_status",
        "column_name": "status",
        "new": "true",
        "passed": "true",
        "failed": "true"
    },
    "_created_at": {
        "name": "_created_at",
        "column_name": "created_at",
        "new": "true",
        "passed": "true",
        "failed": "true"
    },
    "_updated_at": {
        "name": "_updated_at",
        "column_name": "updated_at",
        "new": "true",
        "passed": "true",
        "failed": "true"
    },
    "_deleted_by": {
        "name": "_deleted_by",
        "column_name": "deleted_by",
        "new": "true",
        "passed": "true",
        "failed": "true"
    },
    "_deleted_at": {
        "name": "_deleted_at",
        "column_name": "deleted_at",
        "new": "true",
        "passed": "true",
        "failed": "true"
    },
    "_getSignatures": {
        "name": "_getSignatures",
        "column_name": "getSignatures",
        "new": "true",
        "passed": "true",
        "failed": "true"
    }
}