{
    "_id": {
        "name": "_id",
        "column_name": "id",
        "column_type": "bigint",
        "label": "ID",
        "control": "id",
        "col_span": "12",
        "width": "",
        "hidden_view_all": "",
        "hidden_edit": "",
        "new_line": "",
        "validation": "",
        "formula": ""
    },
    "_name": {
        "name": "_name",
        "column_name": "name",
        "column_type": "string",
        "label": "Title",
        "control": "text",
        "col_span": "12",
        "width": "",
        "hidden_view_all": "",
        "hidden_edit": "",
        "new_line": "",
        "validation": "required",
        "formula": ""
    },
    "_slug": {
        "name": "_slug",
        "column_name": "slug",
        "column_type": "string",
        "label": "Slug",
        "control": "text",
        "col_span": "12",
        "width": "",
        "hidden_view_all": "",
        "hidden_edit": "",
        "new_line": "",
        "validation": "",
        "formula": "All_SlugifyByName"
    },
    "_hse_incident_report_id": {
        "name": "_hse_incident_report_id",
        "column_name": "hse_incident_report_id",
        "column_type": "bigint",
        "label": "Source Doc",
        "control": "dropdown",
        "col_span": "12",
        "width": "",
        "hidden_view_all": "",
        "hidden_edit": "",
        "new_line": "",
        "validation": "required",
        "formula": ""
    },
    "_priority_id": {
        "name": "_priority_id",
        "column_name": "priority_id",
        "column_type": "string",
        "label": "Priority Ranking",
        "control": "text",
        "col_span": "12",
        "width": "",
        "hidden_view_all": "",
        "hidden_edit": "",
        "new_line": "",
        "validation": "required",
        "formula": ""
    },
    "_work_area_id": {
        "name": "_work_area_id",
        "column_name": "work_area_id",
        "column_type": "bigint",
        "label": "Area",
        "control": "dropdown",
        "col_span": "12",
        "width": "",
        "hidden_view_all": "",
        "hidden_edit": "",
        "new_line": "",
        "validation": "required",
        "formula": ""
    },
    "_description": {
        "name": "_description",
        "column_name": "description",
        "column_type": "text",
        "label": "Corrective Action Description",
        "control": "textarea",
        "col_span": "12",
        "width": "",
        "hidden_view_all": "",
        "hidden_edit": "",
        "new_line": "",
        "validation": "",
        "formula": ""
    },
    "_assignee": {
        "name": "_assignee",
        "column_name": "assignee",
        "column_type": "bigint",
        "label": "Responsible by",
        "control": "dropdown",
        "col_span": "12",
        "width": "",
        "hidden_view_all": "",
        "hidden_edit": "",
        "new_line": "",
        "validation": "",
        "formula": ""
    },
    "_opened_date": {
        "name": "_opened_date",
        "column_name": "opened_date",
        "column_type": "datetime",
        "label": "Opened Date",
        "control": "picker_datetime",
        "col_span": "12",
        "width": "",
        "hidden_view_all": "",
        "hidden_edit": "",
        "new_line": "",
        "validation": "",
        "formula": ""
    },
    "_closed_date": {
        "name": "_closed_date",
        "column_name": "closed_date",
        "column_type": "datetime",
        "label": "Closed Date",
        "control": "picker_datetime",
        "col_span": "12",
        "width": "",
        "hidden_view_all": "",
        "hidden_edit": "",
        "new_line": "",
        "validation": "",
        "formula": ""
    },
    "_status": {
        "name": "_status",
        "column_name": "status",
        "column_type": "string",
        "label": "Action Progress",
        "control": "status",
        "col_span": "12",
        "width": "",
        "hidden_view_all": "",
        "hidden_edit": "",
        "new_line": "",
        "validation": "",
        "formula": ""
    },
    "_unsafe_action_type_id": {
        "name": "_unsafe_action_type_id",
        "column_name": "unsafe_action_type_id",
        "column_type": "string",
        "label": "Unsafe Action Type",
        "control": "text",
        "col_span": "12",
        "width": "",
        "hidden_view_all": "",
        "hidden_edit": "",
        "new_line": "",
        "validation": "required",
        "formula": ""
    },
    "_created_at": {
        "name": "_created_at",
        "column_name": "created_at",
        "column_type": "datetime",
        "label": "Created At",
        "control": "picker_datetime",
        "col_span": "12",
        "width": "",
        "hidden_view_all": "true",
        "hidden_edit": "",
        "new_line": "",
        "validation": "",
        "formula": ""
    },
    "_updated_at": {
        "name": "_updated_at",
        "column_name": "updated_at",
        "column_type": "datetime",
        "label": "Updated At",
        "control": "picker_datetime",
        "col_span": "12",
        "width": "",
        "hidden_view_all": "true",
        "hidden_edit": "",
        "new_line": "",
        "validation": "",
        "formula": ""
    }
}