{
    "_id": {
        "name": "_id",
        "column_name": "id",
        "column_type": "bigint",
        "label": "Id",
        "control": "id",
        "col_span": "12",
        "hidden_view_all": "",
        "hidden_edit": "",
        "new_line": "",
        "validation": "",
        "formula": ""
    },
    "_url_thumbnail": {
        "name": "_url_thumbnail",
        "column_name": "url_thumbnail",
        "column_type": "string",
        "label": "Url Thumbnail",
        "control": "text",
        "col_span": "12",
        "hidden_view_all": "",
        "hidden_edit": "",
        "new_line": "",
        "validation": "",
        "formula": ""
    },
    "_url_media": {
        "name": "_url_media",
        "column_name": "url_media",
        "column_type": "string",
        "label": "Url Media",
        "control": "text",
        "col_span": "12",
        "hidden_view_all": "",
        "hidden_edit": "",
        "new_line": "",
        "validation": "",
        "formula": ""
    },
    "_url_folder": {
        "name": "_url_folder",
        "column_name": "url_folder",
        "column_type": "string",
        "label": "Url Folder",
        "control": "text",
        "col_span": "12",
        "hidden_view_all": "true",
        "hidden_edit": "",
        "new_line": "",
        "validation": "",
        "formula": ""
    },
    "_filename": {
        "name": "_filename",
        "column_name": "filename",
        "column_type": "string",
        "label": "Filename",
        "control": "text",
        "col_span": "12",
        "hidden_view_all": "true",
        "hidden_edit": "",
        "new_line": "",
        "validation": "",
        "formula": ""
    },
    "_extension": {
        "name": "_extension",
        "column_name": "extension",
        "column_type": "string",
        "label": "Extension",
        "control": "text",
        "col_span": "12",
        "hidden_view_all": "",
        "hidden_edit": "",
        "new_line": "",
        "validation": "",
        "formula": ""
    },
    "_owner_id": {
        "name": "_owner_id",
        "column_name": "owner_id",
        "column_type": "bigint",
        "label": "Owner Id",
        "control": "dropdown",
        "col_span": "12",
        "hidden_view_all": "",
        "hidden_edit": "",
        "new_line": "",
        "validation": "",
        "formula": ""
    },
    "_object_id": {
        "name": "_object_id",
        "column_name": "object_id",
        "column_type": "bigint",
        "label": "Object Id",
        "control": "number",
        "col_span": "12",
        "hidden_view_all": "true",
        "hidden_edit": "",
        "new_line": "",
        "validation": "",
        "formula": ""
    },
    "_object_type": {
        "name": "_object_type",
        "column_name": "object_type",
        "column_type": "string",
        "label": "Object Type",
        "control": "text",
        "col_span": "12",
        "hidden_view_all": "true",
        "hidden_edit": "",
        "new_line": "",
        "validation": "",
        "formula": ""
    },
    "_category": {
        "name": "_category",
        "column_name": "category",
        "column_type": "bigint",
        "label": "Category",
        "control": "dropdown",
        "col_span": "12",
        "hidden_view_all": "",
        "hidden_edit": "",
        "new_line": "",
        "validation": "",
        "formula": ""
    },
    "_created_at": {
        "name": "_created_at",
        "column_name": "created_at",
        "column_type": "datetime",
        "label": "Created At",
        "control": "picker_datetime",
        "col_span": "12",
        "hidden_view_all": "true",
        "hidden_edit": "",
        "new_line": "",
        "validation": "",
        "formula": ""
    },
    "_updated_at": {
        "name": "_updated_at",
        "column_name": "updated_at",
        "column_type": "datetime",
        "label": "Updated At",
        "control": "picker_datetime",
        "col_span": "12",
        "hidden_view_all": "true",
        "hidden_edit": "",
        "new_line": "",
        "validation": "",
        "formula": ""
    },
    "_mediable": {
        "name": "_mediable",
        "column_name": "mediable",
        "column_type": "ELQ(morphTo)",
        "label": "Mediable",
        "control": "link_morph_to",
        "col_span": "12",
        "hidden_view_all": "",
        "hidden_edit": "",
        "new_line": "",
        "validation": "",
        "formula": ""
    }
}