{
    "_project_id": {
        "name": "_project_id",
        "column_name": "project_id",
        "listen_action": "assign",
        "triggers": "unit_id",
        "listen_to_fields": "unit_id",
        "listen_to_attrs": "project_id",
        "columns_to_set": "",
        "attrs_to_compare": "",
        "expression": "",
        "ajax_response_attribute": "",
        "ajax_form_attributes": "",
        "ajax_item_attributes": "",
        "ajax_default_values": ""
    },
    "_due_date": {
        "name": "_due_date",
        "column_name": "due_date",
        "listen_action": "date_offset",
        "triggers": "priority_id",
        "listen_to_fields": "priority_id",
        "listen_to_attrs": "duration",
        "columns_to_set": "",
        "attrs_to_compare": "id",
        "expression": "",
        "ajax_response_attribute": "",
        "ajax_form_attributes": "",
        "ajax_item_attributes": "",
        "ajax_default_values": ""
    },
    "_defect_sub_cat_id": {
        "name": "_defect_sub_cat_id",
        "column_name": "defect_sub_cat_id",
        "listen_action": "reduce",
        "triggers": "defect_cat_id",
        "listen_to_fields": "defect_sub_cat_id",
        "listen_to_attrs": "defect_cat_id",
        "columns_to_set": "",
        "attrs_to_compare": "id",
        "expression": "",
        "ajax_response_attribute": "",
        "ajax_form_attributes": "",
        "ajax_item_attributes": "",
        "ajax_default_values": ""
    },
    "_id": {
        "name": "_id",
        "column_name": "id",
        "listen_action": "",
        "triggers": "",
        "listen_to_fields": "",
        "listen_to_attrs": "",
        "columns_to_set": "",
        "attrs_to_compare": "",
        "expression": "",
        "ajax_response_attribute": "",
        "ajax_form_attributes": "",
        "ajax_item_attributes": "",
        "ajax_default_values": ""
    },
    "_house_owner_id": {
        "name": "_house_owner_id",
        "column_name": "house_owner_id",
        "listen_action": "",
        "triggers": "",
        "listen_to_fields": "",
        "listen_to_attrs": "",
        "columns_to_set": "",
        "attrs_to_compare": "",
        "expression": "",
        "ajax_response_attribute": "",
        "ajax_form_attributes": "",
        "ajax_item_attributes": "",
        "ajax_default_values": ""
    },
    "_house_owner_phone_number": {
        "name": "_house_owner_phone_number",
        "column_name": "house_owner_phone_number",
        "listen_action": "",
        "triggers": "",
        "listen_to_fields": "",
        "listen_to_attrs": "",
        "columns_to_set": "",
        "attrs_to_compare": "",
        "expression": "",
        "ajax_response_attribute": "",
        "ajax_form_attributes": "",
        "ajax_item_attributes": "",
        "ajax_default_values": ""
    },
    "_house_owner_address": {
        "name": "_house_owner_address",
        "column_name": "house_owner_address",
        "listen_action": "",
        "triggers": "",
        "listen_to_fields": "",
        "listen_to_attrs": "",
        "columns_to_set": "",
        "attrs_to_compare": "",
        "expression": "",
        "ajax_response_attribute": "",
        "ajax_form_attributes": "",
        "ajax_item_attributes": "",
        "ajax_default_values": ""
    },
    "_house_owner_email": {
        "name": "_house_owner_email",
        "column_name": "house_owner_email",
        "listen_action": "",
        "triggers": "",
        "listen_to_fields": "",
        "listen_to_attrs": "",
        "columns_to_set": "",
        "attrs_to_compare": "",
        "expression": "",
        "ajax_response_attribute": "",
        "ajax_form_attributes": "",
        "ajax_item_attributes": "",
        "ajax_default_values": ""
    },
    "_name": {
        "name": "_name",
        "column_name": "name",
        "listen_action": "",
        "triggers": "",
        "listen_to_fields": "",
        "listen_to_attrs": "",
        "columns_to_set": "",
        "attrs_to_compare": "",
        "expression": "",
        "ajax_response_attribute": "",
        "ajax_form_attributes": "",
        "ajax_item_attributes": "",
        "ajax_default_values": ""
    },
    "_description": {
        "name": "_description",
        "column_name": "description",
        "listen_action": "",
        "triggers": "",
        "listen_to_fields": "",
        "listen_to_attrs": "",
        "columns_to_set": "",
        "attrs_to_compare": "",
        "expression": "",
        "ajax_response_attribute": "",
        "ajax_form_attributes": "",
        "ajax_item_attributes": "",
        "ajax_default_values": ""
    },
    "_unit_id": {
        "name": "_unit_id",
        "column_name": "unit_id",
        "listen_action": "",
        "triggers": "",
        "listen_to_fields": "",
        "listen_to_attrs": "",
        "columns_to_set": "",
        "attrs_to_compare": "",
        "expression": "",
        "ajax_response_attribute": "",
        "ajax_form_attributes": "",
        "ajax_item_attributes": "",
        "ajax_default_values": ""
    },
    "_priority_id": {
        "name": "_priority_id",
        "column_name": "priority_id",
        "listen_action": "",
        "triggers": "",
        "listen_to_fields": "",
        "listen_to_attrs": "",
        "columns_to_set": "",
        "attrs_to_compare": "",
        "expression": "",
        "ajax_response_attribute": "",
        "ajax_form_attributes": "",
        "ajax_item_attributes": "",
        "ajax_default_values": ""
    },
    "_defect_cat_id": {
        "name": "_defect_cat_id",
        "column_name": "defect_cat_id",
        "listen_action": "",
        "triggers": "",
        "listen_to_fields": "",
        "listen_to_attrs": "",
        "columns_to_set": "",
        "attrs_to_compare": "",
        "expression": "",
        "ajax_response_attribute": "",
        "ajax_form_attributes": "",
        "ajax_item_attributes": "",
        "ajax_default_values": ""
    },
    "_opened_photos": {
        "name": "_opened_photos",
        "column_name": "opened_photos",
        "listen_action": "",
        "triggers": "",
        "listen_to_fields": "",
        "listen_to_attrs": "",
        "columns_to_set": "",
        "attrs_to_compare": "",
        "expression": "",
        "ajax_response_attribute": "",
        "ajax_form_attributes": "",
        "ajax_item_attributes": "",
        "ajax_default_values": ""
    },
    "_appointment_title": {
        "name": "_appointment_title",
        "column_name": "appointment_title",
        "listen_action": "",
        "triggers": "",
        "listen_to_fields": "",
        "listen_to_attrs": "",
        "columns_to_set": "",
        "attrs_to_compare": "",
        "expression": "",
        "ajax_response_attribute": "",
        "ajax_form_attributes": "",
        "ajax_item_attributes": "",
        "ajax_default_values": ""
    },
    "_assignee_1": {
        "name": "_assignee_1",
        "column_name": "assignee_1",
        "listen_action": "",
        "triggers": "",
        "listen_to_fields": "",
        "listen_to_attrs": "",
        "columns_to_set": "",
        "attrs_to_compare": "",
        "expression": "",
        "ajax_response_attribute": "",
        "ajax_form_attributes": "",
        "ajax_item_attributes": "",
        "ajax_default_values": ""
    },
    "_appointment_from": {
        "name": "_appointment_from",
        "column_name": "appointment_from",
        "listen_action": "",
        "triggers": "",
        "listen_to_fields": "",
        "listen_to_attrs": "",
        "columns_to_set": "",
        "attrs_to_compare": "",
        "expression": "",
        "ajax_response_attribute": "",
        "ajax_form_attributes": "",
        "ajax_item_attributes": "",
        "ajax_default_values": ""
    },
    "_appointment_to": {
        "name": "_appointment_to",
        "column_name": "appointment_to",
        "listen_action": "",
        "triggers": "",
        "listen_to_fields": "",
        "listen_to_attrs": "",
        "columns_to_set": "",
        "attrs_to_compare": "",
        "expression": "",
        "ajax_response_attribute": "",
        "ajax_form_attributes": "",
        "ajax_item_attributes": "",
        "ajax_default_values": ""
    },
    "_appointment_detail": {
        "name": "_appointment_detail",
        "column_name": "appointment_detail",
        "listen_action": "",
        "triggers": "",
        "listen_to_fields": "",
        "listen_to_attrs": "",
        "columns_to_set": "",
        "attrs_to_compare": "",
        "expression": "",
        "ajax_response_attribute": "",
        "ajax_form_attributes": "",
        "ajax_item_attributes": "",
        "ajax_default_values": ""
    },
    "_getMonitors1": {
        "name": "_getMonitors1",
        "column_name": "getMonitors1",
        "listen_action": "",
        "triggers": "",
        "listen_to_fields": "",
        "listen_to_attrs": "",
        "columns_to_set": "",
        "attrs_to_compare": "",
        "expression": "",
        "ajax_response_attribute": "",
        "ajax_form_attributes": "",
        "ajax_item_attributes": "",
        "ajax_default_values": ""
    },
    "_getTicketingTasks": {
        "name": "_getTicketingTasks",
        "column_name": "getTicketingTasks",
        "listen_action": "",
        "triggers": "",
        "listen_to_fields": "",
        "listen_to_attrs": "",
        "columns_to_set": "",
        "attrs_to_compare": "",
        "expression": "",
        "ajax_response_attribute": "",
        "ajax_form_attributes": "",
        "ajax_item_attributes": "",
        "ajax_default_values": ""
    },
    "_closed_photos": {
        "name": "_closed_photos",
        "column_name": "closed_photos",
        "listen_action": "",
        "triggers": "",
        "listen_to_fields": "",
        "listen_to_attrs": "",
        "columns_to_set": "",
        "attrs_to_compare": "",
        "expression": "",
        "ajax_response_attribute": "",
        "ajax_form_attributes": "",
        "ajax_item_attributes": "",
        "ajax_default_values": ""
    },
    "_owner_id": {
        "name": "_owner_id",
        "column_name": "owner_id",
        "listen_action": "",
        "triggers": "",
        "listen_to_fields": "",
        "listen_to_attrs": "",
        "columns_to_set": "",
        "attrs_to_compare": "",
        "expression": "",
        "ajax_response_attribute": "",
        "ajax_form_attributes": "",
        "ajax_item_attributes": "",
        "ajax_default_values": ""
    },
    "_created_at": {
        "name": "_created_at",
        "column_name": "created_at",
        "listen_action": "",
        "triggers": "",
        "listen_to_fields": "",
        "listen_to_attrs": "",
        "columns_to_set": "",
        "attrs_to_compare": "",
        "expression": "",
        "ajax_response_attribute": "",
        "ajax_form_attributes": "",
        "ajax_item_attributes": "",
        "ajax_default_values": ""
    },
    "_updated_at": {
        "name": "_updated_at",
        "column_name": "updated_at",
        "listen_action": "",
        "triggers": "",
        "listen_to_fields": "",
        "listen_to_attrs": "",
        "columns_to_set": "",
        "attrs_to_compare": "",
        "expression": "",
        "ajax_response_attribute": "",
        "ajax_form_attributes": "",
        "ajax_item_attributes": "",
        "ajax_default_values": ""
    },
    "_deleted_by": {
        "name": "_deleted_by",
        "column_name": "deleted_by",
        "listen_action": "",
        "triggers": "",
        "listen_to_fields": "",
        "listen_to_attrs": "",
        "columns_to_set": "",
        "attrs_to_compare": "",
        "expression": "",
        "ajax_response_attribute": "",
        "ajax_form_attributes": "",
        "ajax_item_attributes": "",
        "ajax_default_values": ""
    },
    "_deleted_at": {
        "name": "_deleted_at",
        "column_name": "deleted_at",
        "listen_action": "",
        "triggers": "",
        "listen_to_fields": "",
        "listen_to_attrs": "",
        "columns_to_set": "",
        "attrs_to_compare": "",
        "expression": "",
        "ajax_response_attribute": "",
        "ajax_form_attributes": "",
        "ajax_item_attributes": "",
        "ajax_default_values": ""
    },
    "_status": {
        "name": "_status",
        "column_name": "status",
        "listen_action": "",
        "triggers": "",
        "listen_to_fields": "",
        "listen_to_attrs": "",
        "columns_to_set": "",
        "attrs_to_compare": "",
        "expression": "",
        "ajax_response_attribute": "",
        "ajax_form_attributes": "",
        "ajax_item_attributes": "",
        "ajax_default_values": ""
    }
}