{
    "_id": {
        "name": "_id",
        "column_name": "id",
        "column_type": "bigint unsigned",
        "label": "",
        "control": "",
        "align": "",
        "col_span": "",
        "width": "",
        "hidden_view_all": "",
        "hidden_edit": "",
        "hidden_label": "",
        "hidden_filter": "",
        "hidden_print": "",
        "read_only": "",
        "save_on_change": "",
        "duplicatable": "",
        "new_line": "",
        "frozen_left": "",
        "frozen_right": "",
        "nowrap_view_all": ""
    },
    "_section_owner_info": {
        "name": "_section_owner_info",
        "column_name": "section_owner_info",
        "column_type": "static",
        "label": "Requester Infomation",
        "control": "z_h4",
        "align": "",
        "col_span": "12",
        "width": "",
        "hidden_view_all": "",
        "hidden_edit": "",
        "hidden_label": "",
        "hidden_filter": "",
        "hidden_print": "",
        "read_only": "",
        "save_on_change": "",
        "duplicatable": "",
        "new_line": "",
        "frozen_left": "",
        "frozen_right": "",
        "nowrap_view_all": ""
    },
    "_section_owner_info_sub": {
        "name": "_section_owner_info_sub",
        "column_name": "section_owner_info_sub",
        "column_type": "static",
        "label": "Complete by Requester",
        "control": "z_h6_base",
        "align": "",
        "col_span": "12",
        "width": "",
        "hidden_view_all": "",
        "hidden_edit": "",
        "hidden_label": "",
        "hidden_filter": "",
        "hidden_print": "",
        "read_only": "",
        "save_on_change": "",
        "duplicatable": "",
        "new_line": "",
        "frozen_left": "",
        "frozen_right": "",
        "nowrap_view_all": ""
    },
    "_house_owner_id": {
        "name": "_house_owner_id",
        "column_name": "house_owner_id",
        "column_type": "varchar(255)",
        "label": "House Owner",
        "control": "dropdown",
        "align": "",
        "col_span": "6",
        "width": "",
        "hidden_view_all": "",
        "hidden_edit": "",
        "hidden_label": "",
        "hidden_filter": "",
        "hidden_print": "",
        "read_only": "",
        "save_on_change": "",
        "duplicatable": "",
        "new_line": "",
        "frozen_left": "",
        "frozen_right": "",
        "nowrap_view_all": ""
    },
    "_house_owner_phone_number": {
        "name": "_house_owner_phone_number",
        "column_name": "house_owner_phone_number",
        "column_type": "varchar(255)",
        "label": "Phone",
        "control": "text",
        "align": "",
        "col_span": "6",
        "width": "",
        "hidden_view_all": "",
        "hidden_edit": "",
        "hidden_label": "",
        "hidden_filter": "",
        "hidden_print": "",
        "read_only": "",
        "save_on_change": "",
        "duplicatable": "",
        "new_line": "",
        "frozen_left": "",
        "frozen_right": "",
        "nowrap_view_all": ""
    },
    "_house_owner_address": {
        "name": "_house_owner_address",
        "column_name": "house_owner_address",
        "column_type": "varchar(255)",
        "label": "Address",
        "control": "text",
        "align": "",
        "col_span": "6",
        "width": "",
        "hidden_view_all": "",
        "hidden_edit": "",
        "hidden_label": "",
        "hidden_filter": "",
        "hidden_print": "",
        "read_only": "",
        "save_on_change": "",
        "duplicatable": "",
        "new_line": "",
        "frozen_left": "",
        "frozen_right": "",
        "nowrap_view_all": ""
    },
    "_house_owner_email": {
        "name": "_house_owner_email",
        "column_name": "house_owner_email",
        "column_type": "varchar(255)",
        "label": "Email",
        "control": "text",
        "align": "",
        "col_span": "6",
        "width": "",
        "hidden_view_all": "",
        "hidden_edit": "",
        "hidden_label": "",
        "hidden_filter": "",
        "hidden_print": "",
        "read_only": "",
        "save_on_change": "",
        "duplicatable": "",
        "new_line": "",
        "frozen_left": "",
        "frozen_right": "",
        "nowrap_view_all": ""
    },
    "_sep00": {
        "name": "_sep00",
        "column_name": "sep00",
        "column_type": "static",
        "label": "Sep00",
        "control": "z_divider",
        "align": "",
        "col_span": "12",
        "width": "",
        "hidden_view_all": "",
        "hidden_edit": "",
        "hidden_label": "",
        "hidden_filter": "",
        "hidden_print": "",
        "read_only": "",
        "save_on_change": "",
        "duplicatable": "",
        "new_line": "",
        "frozen_left": "",
        "frozen_right": "",
        "nowrap_view_all": ""
    },
    "_section_basic_info": {
        "name": "_section_basic_info",
        "column_name": "section_basic_info",
        "column_type": "static",
        "label": "Ticket Information",
        "control": "z_h4",
        "align": "",
        "col_span": "12",
        "width": "",
        "hidden_view_all": "",
        "hidden_edit": "",
        "hidden_label": "",
        "hidden_filter": "",
        "hidden_print": "",
        "read_only": "",
        "save_on_change": "",
        "duplicatable": "",
        "new_line": "",
        "frozen_left": "",
        "frozen_right": "",
        "nowrap_view_all": ""
    },
    "_section_basic_info_sub": {
        "name": "_section_basic_info_sub",
        "column_name": "section_basic_info_sub",
        "column_type": "static",
        "label": "Complete by House Owner",
        "control": "z_h6_base",
        "align": "",
        "col_span": "12",
        "width": "",
        "hidden_view_all": "",
        "hidden_edit": "",
        "hidden_label": "",
        "hidden_filter": "",
        "hidden_print": "",
        "read_only": "",
        "save_on_change": "",
        "duplicatable": "",
        "new_line": "",
        "frozen_left": "",
        "frozen_right": "",
        "nowrap_view_all": ""
    },
    "_name": {
        "name": "_name",
        "column_name": "name",
        "column_type": "varchar(255)",
        "label": "Title of the Ticket",
        "control": "text",
        "align": "",
        "col_span": "",
        "width": "",
        "hidden_view_all": "",
        "hidden_edit": "",
        "hidden_label": "",
        "hidden_filter": "",
        "hidden_print": "",
        "read_only": "",
        "save_on_change": "",
        "duplicatable": "",
        "new_line": "",
        "frozen_left": "",
        "frozen_right": "",
        "nowrap_view_all": ""
    },
    "_description": {
        "name": "_description",
        "column_name": "description",
        "column_type": "text",
        "label": "Description",
        "control": "textarea",
        "align": "",
        "col_span": "",
        "width": "",
        "hidden_view_all": "",
        "hidden_edit": "",
        "hidden_label": "",
        "hidden_filter": "",
        "hidden_print": "",
        "read_only": "",
        "save_on_change": "",
        "duplicatable": "",
        "new_line": "",
        "frozen_left": "",
        "frozen_right": "",
        "nowrap_view_all": ""
    },
    "_unit_id": {
        "name": "_unit_id",
        "column_name": "unit_id",
        "column_type": "bigint unsigned",
        "label": "Apartment\/Unit number",
        "control": "dropdown",
        "align": "",
        "col_span": "6",
        "width": "",
        "hidden_view_all": "",
        "hidden_edit": "",
        "hidden_label": "",
        "hidden_filter": "",
        "hidden_print": "",
        "read_only": "",
        "save_on_change": "",
        "duplicatable": "",
        "new_line": "",
        "frozen_left": "",
        "frozen_right": "",
        "nowrap_view_all": ""
    },
    "_project_id": {
        "name": "_project_id",
        "column_name": "project_id",
        "column_type": "bigint unsigned",
        "label": "Project",
        "control": "dropdown",
        "align": "",
        "col_span": "6",
        "width": "",
        "hidden_view_all": "",
        "hidden_edit": "",
        "hidden_label": "",
        "hidden_filter": "",
        "hidden_print": "",
        "read_only": "",
        "save_on_change": "",
        "duplicatable": "",
        "new_line": "",
        "frozen_left": "",
        "frozen_right": "",
        "nowrap_view_all": ""
    },
    "_priority_id": {
        "name": "_priority_id",
        "column_name": "priority_id",
        "column_type": "bigint unsigned",
        "label": "Priority",
        "control": "dropdown",
        "align": "",
        "col_span": "6",
        "width": "",
        "hidden_view_all": "",
        "hidden_edit": "",
        "hidden_label": "",
        "hidden_filter": "",
        "hidden_print": "",
        "read_only": "",
        "save_on_change": "",
        "duplicatable": "",
        "new_line": "",
        "frozen_left": "",
        "frozen_right": "",
        "nowrap_view_all": ""
    },
    "_due_date": {
        "name": "_due_date",
        "column_name": "due_date",
        "column_type": "datetime",
        "label": "Due date",
        "control": "picker_datetime",
        "align": "",
        "col_span": "6",
        "width": "",
        "hidden_view_all": "",
        "hidden_edit": "",
        "hidden_label": "",
        "hidden_filter": "",
        "hidden_print": "",
        "read_only": "",
        "save_on_change": "",
        "duplicatable": "",
        "new_line": "",
        "frozen_left": "",
        "frozen_right": "",
        "nowrap_view_all": ""
    },
    "_defect_cat_id": {
        "name": "_defect_cat_id",
        "column_name": "defect_cat_id",
        "column_type": "bigint unsigned",
        "label": "Defect Category",
        "control": "dropdown",
        "align": "",
        "col_span": "6",
        "width": "",
        "hidden_view_all": "",
        "hidden_edit": "",
        "hidden_label": "",
        "hidden_filter": "",
        "hidden_print": "",
        "read_only": "",
        "save_on_change": "",
        "duplicatable": "",
        "new_line": "",
        "frozen_left": "",
        "frozen_right": "",
        "nowrap_view_all": ""
    },
    "_defect_sub_cat_id": {
        "name": "_defect_sub_cat_id",
        "column_name": "defect_sub_cat_id",
        "column_type": "bigint unsigned",
        "label": "Defect Detail",
        "control": "dropdown",
        "align": "",
        "col_span": "6",
        "width": "",
        "hidden_view_all": "",
        "hidden_edit": "",
        "hidden_label": "",
        "hidden_filter": "",
        "hidden_print": "",
        "read_only": "",
        "save_on_change": "",
        "duplicatable": "",
        "new_line": "",
        "frozen_left": "",
        "frozen_right": "",
        "nowrap_view_all": ""
    },
    "_opened_photos": {
        "name": "_opened_photos",
        "column_name": "opened_photos",
        "column_type": "morphMany",
        "label": "Defective Photos",
        "control": "attachment",
        "align": "",
        "col_span": "",
        "width": "",
        "hidden_view_all": "",
        "hidden_edit": "",
        "hidden_label": "",
        "hidden_filter": "",
        "hidden_print": "",
        "read_only": "",
        "save_on_change": "",
        "duplicatable": "",
        "new_line": "",
        "frozen_left": "",
        "frozen_right": "",
        "nowrap_view_all": ""
    },
    "_sep01": {
        "name": "_sep01",
        "column_name": "sep01",
        "column_type": "static",
        "label": "Sep01",
        "control": "z_divider",
        "align": "",
        "col_span": "12",
        "width": "",
        "hidden_view_all": "",
        "hidden_edit": "",
        "hidden_label": "",
        "hidden_filter": "",
        "hidden_print": "",
        "read_only": "",
        "save_on_change": "",
        "duplicatable": "",
        "new_line": "",
        "frozen_left": "",
        "frozen_right": "",
        "nowrap_view_all": ""
    },
    "_section_appointment": {
        "name": "_section_appointment",
        "column_name": "section_appointment",
        "column_type": "static",
        "label": "Appointment",
        "control": "z_h4",
        "align": "",
        "col_span": "12",
        "width": "",
        "hidden_view_all": "",
        "hidden_edit": "",
        "hidden_label": "",
        "hidden_filter": "",
        "hidden_print": "",
        "read_only": "",
        "save_on_change": "",
        "duplicatable": "",
        "new_line": "",
        "frozen_left": "",
        "frozen_right": "",
        "nowrap_view_all": ""
    },
    "_section_appointment_sub": {
        "name": "_section_appointment_sub",
        "column_name": "section_appointment_sub",
        "column_type": "static",
        "label": "Complete by Internals\/Sub-contractor",
        "control": "z_h6_base",
        "align": "",
        "col_span": "12",
        "width": "",
        "hidden_view_all": "",
        "hidden_edit": "",
        "hidden_label": "",
        "hidden_filter": "",
        "hidden_print": "",
        "read_only": "",
        "save_on_change": "",
        "duplicatable": "",
        "new_line": "",
        "frozen_left": "",
        "frozen_right": "",
        "nowrap_view_all": ""
    },
    "_appointment_title": {
        "name": "_appointment_title",
        "column_name": "appointment_title",
        "column_type": "varchar(255)",
        "label": "Appointment Title",
        "control": "text",
        "align": "",
        "col_span": "6",
        "width": "",
        "hidden_view_all": "",
        "hidden_edit": "",
        "hidden_label": "",
        "hidden_filter": "",
        "hidden_print": "",
        "read_only": "",
        "save_on_change": "",
        "duplicatable": "",
        "new_line": "",
        "frozen_left": "",
        "frozen_right": "",
        "nowrap_view_all": ""
    },
    "_assignee_1": {
        "name": "_assignee_1",
        "column_name": "assignee_1",
        "column_type": "bigint unsigned",
        "label": "Supporter",
        "control": "dropdown",
        "align": "",
        "col_span": "6",
        "width": "",
        "hidden_view_all": "",
        "hidden_edit": "",
        "hidden_label": "",
        "hidden_filter": "",
        "hidden_print": "",
        "read_only": "",
        "save_on_change": "",
        "duplicatable": "",
        "new_line": "",
        "frozen_left": "",
        "frozen_right": "",
        "nowrap_view_all": ""
    },
    "_appointment_from": {
        "name": "_appointment_from",
        "column_name": "appointment_from",
        "column_type": "datetime",
        "label": "From",
        "control": "picker_datetime",
        "align": "",
        "col_span": "6",
        "width": "",
        "hidden_view_all": "",
        "hidden_edit": "",
        "hidden_label": "",
        "hidden_filter": "",
        "hidden_print": "",
        "read_only": "",
        "save_on_change": "",
        "duplicatable": "",
        "new_line": "",
        "frozen_left": "",
        "frozen_right": "",
        "nowrap_view_all": ""
    },
    "_appointment_to": {
        "name": "_appointment_to",
        "column_name": "appointment_to",
        "column_type": "datetime",
        "label": "To",
        "control": "picker_datetime",
        "align": "",
        "col_span": "6",
        "width": "",
        "hidden_view_all": "",
        "hidden_edit": "",
        "hidden_label": "",
        "hidden_filter": "",
        "hidden_print": "",
        "read_only": "",
        "save_on_change": "",
        "duplicatable": "",
        "new_line": "",
        "frozen_left": "",
        "frozen_right": "",
        "nowrap_view_all": ""
    },
    "_appointment_detail": {
        "name": "_appointment_detail",
        "column_name": "appointment_detail",
        "column_type": "varchar(255)",
        "label": "Appointment Detail",
        "control": "textarea",
        "align": "",
        "col_span": "",
        "width": "",
        "hidden_view_all": "",
        "hidden_edit": "",
        "hidden_label": "",
        "hidden_filter": "",
        "hidden_print": "",
        "read_only": "",
        "save_on_change": "",
        "duplicatable": "",
        "new_line": "",
        "frozen_left": "",
        "frozen_right": "",
        "nowrap_view_all": ""
    },
    "_getMonitors1": {
        "name": "_getMonitors1",
        "column_name": "getMonitors1",
        "column_type": "belongsToMany",
        "label": "Monitors",
        "control": "dropdown_multi_2a",
        "align": "",
        "col_span": "",
        "width": "",
        "hidden_view_all": "",
        "hidden_edit": "",
        "hidden_label": "",
        "hidden_filter": "",
        "hidden_print": "",
        "read_only": "",
        "save_on_change": "",
        "duplicatable": "",
        "new_line": "",
        "frozen_left": "",
        "frozen_right": "",
        "nowrap_view_all": ""
    },
    "_comment_ticketing": {
        "name": "_comment_ticketing",
        "column_name": "comment_ticketing",
        "column_type": "morphMany",
        "label": "Comment",
        "control": "comment",
        "align": "",
        "col_span": "",
        "width": "",
        "hidden_view_all": "",
        "hidden_edit": "",
        "hidden_label": "",
        "hidden_filter": "",
        "hidden_print": "",
        "read_only": "",
        "save_on_change": "",
        "duplicatable": "",
        "new_line": "",
        "frozen_left": "",
        "frozen_right": "",
        "nowrap_view_all": ""
    },
    "_sep02": {
        "name": "_sep02",
        "column_name": "sep02",
        "column_type": "static",
        "label": "Sep02",
        "control": "z_divider",
        "align": "",
        "col_span": "12",
        "width": "",
        "hidden_view_all": "",
        "hidden_edit": "",
        "hidden_label": "",
        "hidden_filter": "",
        "hidden_print": "",
        "read_only": "",
        "save_on_change": "",
        "duplicatable": "",
        "new_line": "",
        "frozen_left": "",
        "frozen_right": "",
        "nowrap_view_all": ""
    },
    "_section_task": {
        "name": "_section_task",
        "column_name": "section_task",
        "column_type": "static",
        "label": "Task Details",
        "control": "z_h4",
        "align": "",
        "col_span": "12",
        "width": "",
        "hidden_view_all": "",
        "hidden_edit": "",
        "hidden_label": "",
        "hidden_filter": "",
        "hidden_print": "",
        "read_only": "",
        "save_on_change": "",
        "duplicatable": "",
        "new_line": "",
        "frozen_left": "",
        "frozen_right": "",
        "nowrap_view_all": ""
    },
    "_section_task_sub": {
        "name": "_section_task_sub",
        "column_name": "section_task_sub",
        "column_type": "static",
        "label": "Complete by Internals\/Sub-contractor",
        "control": "z_h6_base",
        "align": "",
        "col_span": "12",
        "width": "",
        "hidden_view_all": "",
        "hidden_edit": "",
        "hidden_label": "",
        "hidden_filter": "",
        "hidden_print": "",
        "read_only": "",
        "save_on_change": "",
        "duplicatable": "",
        "new_line": "",
        "frozen_left": "",
        "frozen_right": "",
        "nowrap_view_all": ""
    },
    "_getTicketingTasks": {
        "name": "_getTicketingTasks",
        "column_name": "getTicketingTasks",
        "column_type": "hasMany",
        "label": "Tasks",
        "control": "relationship_renderer",
        "align": "",
        "col_span": "",
        "width": "",
        "hidden_view_all": "",
        "hidden_edit": "",
        "hidden_label": "true",
        "hidden_filter": "",
        "hidden_print": "",
        "read_only": "",
        "save_on_change": "",
        "duplicatable": "",
        "new_line": "true",
        "frozen_left": "",
        "frozen_right": "",
        "nowrap_view_all": ""
    },
    "_closed_photos": {
        "name": "_closed_photos",
        "column_name": "closed_photos",
        "column_type": "morphMany",
        "label": "Corrective Photos",
        "control": "attachment",
        "align": "",
        "col_span": "",
        "width": "",
        "hidden_view_all": "",
        "hidden_edit": "",
        "hidden_label": "",
        "hidden_filter": "",
        "hidden_print": "",
        "read_only": "",
        "save_on_change": "",
        "duplicatable": "",
        "new_line": "",
        "frozen_left": "",
        "frozen_right": "",
        "nowrap_view_all": ""
    },
    "_owner_id": {
        "name": "_owner_id",
        "column_name": "owner_id",
        "column_type": "bigint unsigned",
        "label": "Creator",
        "control": "dropdown",
        "align": "",
        "col_span": "",
        "width": "",
        "hidden_view_all": "",
        "hidden_edit": "true",
        "hidden_label": "",
        "hidden_filter": "",
        "hidden_print": "",
        "read_only": "",
        "save_on_change": "",
        "duplicatable": "",
        "new_line": "",
        "frozen_left": "",
        "frozen_right": "",
        "nowrap_view_all": ""
    },
    "_created_at": {
        "name": "_created_at",
        "column_name": "created_at",
        "column_type": "timestamp",
        "label": "",
        "control": "",
        "align": "",
        "col_span": "",
        "width": "",
        "hidden_view_all": "",
        "hidden_edit": "",
        "hidden_label": "",
        "hidden_filter": "",
        "hidden_print": "",
        "read_only": "",
        "save_on_change": "",
        "duplicatable": "",
        "new_line": "",
        "frozen_left": "",
        "frozen_right": "",
        "nowrap_view_all": ""
    },
    "_updated_at": {
        "name": "_updated_at",
        "column_name": "updated_at",
        "column_type": "timestamp",
        "label": "",
        "control": "",
        "align": "",
        "col_span": "",
        "width": "",
        "hidden_view_all": "",
        "hidden_edit": "",
        "hidden_label": "",
        "hidden_filter": "",
        "hidden_print": "",
        "read_only": "",
        "save_on_change": "",
        "duplicatable": "",
        "new_line": "",
        "frozen_left": "",
        "frozen_right": "",
        "nowrap_view_all": ""
    },
    "_deleted_by": {
        "name": "_deleted_by",
        "column_name": "deleted_by",
        "column_type": "bigint unsigned",
        "label": "",
        "control": "",
        "align": "",
        "col_span": "",
        "width": "",
        "hidden_view_all": "",
        "hidden_edit": "",
        "hidden_label": "",
        "hidden_filter": "",
        "hidden_print": "",
        "read_only": "",
        "save_on_change": "",
        "duplicatable": "",
        "new_line": "",
        "frozen_left": "",
        "frozen_right": "",
        "nowrap_view_all": ""
    },
    "_deleted_at": {
        "name": "_deleted_at",
        "column_name": "deleted_at",
        "column_type": "timestamp",
        "label": "",
        "control": "",
        "align": "",
        "col_span": "",
        "width": "",
        "hidden_view_all": "",
        "hidden_edit": "",
        "hidden_label": "",
        "hidden_filter": "",
        "hidden_print": "",
        "read_only": "",
        "save_on_change": "",
        "duplicatable": "",
        "new_line": "",
        "frozen_left": "",
        "frozen_right": "",
        "nowrap_view_all": ""
    },
    "_status": {
        "name": "_status",
        "column_name": "status",
        "column_type": "varchar(255)",
        "label": "Status",
        "control": "",
        "align": "",
        "col_span": "",
        "width": "",
        "hidden_view_all": "",
        "hidden_edit": "",
        "hidden_label": "",
        "hidden_filter": "",
        "hidden_print": "",
        "read_only": "",
        "save_on_change": "",
        "duplicatable": "",
        "new_line": "",
        "frozen_left": "",
        "frozen_right": "",
        "nowrap_view_all": ""
    }
}